fastflow/__init__.py
fastflow/__main__.py
fastflow/cli.py
fastflow/kubernetes.py
fastflow/models.py
fastflow/setup.py
fastflow/engine/__init__.py
fastflow/engine/lifecycle.py
fastflow/engine/models.py
fastflow/engine/task_handlers.py
fastflow/engine/utils.py
fastflow/engine/workflow_handlers.py
fastflow/tasks/__init__.py
fastflow/tasks/http.py
fastflow/tasks/stdlib.py
python_fastflow-0.8.1.dist-info/LICENSE
python_fastflow-0.8.1.dist-info/METADATA
python_fastflow-0.8.1.dist-info/WHEEL
python_fastflow-0.8.1.dist-info/entry_points.txt
python_fastflow-0.8.1.dist-info/top_level.txt
python_fastflow-0.8.1.dist-info/RECORD
