Metadata-Version: 2.1
Name: python-fastflow
Version: 0.8.1
Summary: A workflow engine based on Kopf
Author-email: Steffen Vinther Sørensen <svinther@gmail.com>
License: MIT License
Project-URL: Homepage, https://github.com/svinther/fastflow
Classifier: Intended Audience :: Developers
Classifier: License :: OSI Approved :: MIT License
Classifier: Operating System :: OS Independent
Classifier: Programming Language :: Python
Classifier: Programming Language :: Python :: 3
Classifier: Programming Language :: Python :: 3.11
Classifier: Programming Language :: Python :: 3.10
Classifier: Programming Language :: Python :: 3.9
Classifier: Programming Language :: Python :: 3 :: Only
Classifier: Topic :: Software Development :: Libraries
Requires-Python: >=3.9
License-File: LICENSE
Requires-Dist: kopf==1.37.2
Requires-Dist: python-dotenv==1.0.1
Requires-Dist: kubernetes_asyncio==30.3.1
Requires-Dist: kubernetes==30.1.0
Requires-Dist: Jinja2==3.1.4
Requires-Dist: networkx==3.4.2
Requires-Dist: pydantic[email]==2.9.1
Requires-Dist: pydantic-settings==2.6.0
Requires-Dist: PyYAML==6.0.1
Requires-Dist: click==8.1.7
